{"cameraMode":{"drawMode":0,"name":"Shaded","section":"Shading Mode"},"sceneLighting":false,"audioPlay":false,"sceneViewState":{"showFog":true,"showMaterialUpdate":false,"showSkybox":false,"showFlares":true,"showImageEffects":true,"showParticleSystems":true},"in2DMode":false,"pivot":{"x":0.08739102631807327,"y":0.028075892478227617,"z":0.039546504616737369},"rotation":{"x":0.08826594054698944,"y":-0.9107891321182251,"z":0.2982213795185089,"w":0.2720552682876587},"size":0.5094839334487915,"orthographic":false}